MANIFEST.in
account_chart.xml
account_tax.xml
account_tax_code.xml
l10n_vn_wizard.xml
setup.py
./__init__.py
./__openerp__.py
openerp_l10n_vn.egg-info/PKG-INFO
openerp_l10n_vn.egg-info/SOURCES.txt
openerp_l10n_vn.egg-info/dependency_links.txt
openerp_l10n_vn.egg-info/requires.txt
openerp_l10n_vn.egg-info/top_level.txt
static/src/img/icon.png